pytest_qasync/__init__.py
pytest_qasync/plugin.py
pytest_qasync-0.0.1.dist-info/LICENSE
pytest_qasync-0.0.1.dist-info/METADATA
pytest_qasync-0.0.1.dist-info/WHEEL
pytest_qasync-0.0.1.dist-info/entry_points.txt
pytest_qasync-0.0.1.dist-info/top_level.txt
pytest_qasync-0.0.1.dist-info/RECORD
